pygenstrings/__init__.py
pygenstrings/cli.py
pygenstrings/genstrings.py
pygenstrings/parser.py
pygenstrings-19.5.dist-info/entry_points.txt
pygenstrings-19.5.dist-info/WHEEL
pygenstrings-19.5.dist-info/METADATA
pygenstrings-19.5.dist-info/RECORD
