Metadata-Version: 2.1
Name: pygenstrings
Version: 19.5
Summary: Simplifies managing localization files for ObjC/Swift projects.
Home-page: UNKNOWN
License: UNKNOWN
Author: Jonas Obrist
Author-email: jonas.obrist@hde.co.jp
Requires-Python: >=3.7,<4.0
Classifier: Programming Language :: Python :: 3
Classifier: Programming Language :: Python :: 3.7
Requires-Dist: chardet (>=3.0,<4.0)
Requires-Dist: click (>=7.0,<8.0)
Requires-Dist: toml (>=0.10.0,<0.11.0)
